LICENSE
README.md
setup.py
pyForecasting/__init__.py
pyForecasting.egg-info/PKG-INFO
pyForecasting.egg-info/SOURCES.txt
pyForecasting.egg-info/dependency_links.txt
pyForecasting.egg-info/requires.txt
pyForecasting.egg-info/top_level.txt
tests/__init__.py